py.typed
pytest_kedge.py
pytest_kedge.pyi
pytest_kedge-0.1.1.dist-info/METADATA
pytest_kedge-0.1.1.dist-info/WHEEL
pytest_kedge-0.1.1.dist-info/entry_points.txt
pytest_kedge-0.1.1.dist-info/licenses/LICENSE
pytest_kedge-0.1.1.dist-info/RECORD
