Metadata-Version: 2.4
Name: pytest-kedge
Version: 0.1.1
Summary: Agent-friendly structured test data collector for pytest
Author: Pete Bowman
License-File: LICENSE
Requires-Python: >=3.11
Requires-Dist: pytest>=7.0.0
